{
  "interactionModel": {
      "languageModel": {
          "invocationName": "dice roller",
          "intents": [
              {
                  "name": "RollDiceIntent",
                  "slots": [
                      {
                          "name": "AddToHighScore",
                          "type": "AddToHighScore"
                      },
                      {
                          "name": "name",
                          "type": "AMAZON.US_FIRST_NAME"
                      }
                  ],
                  "samples": [
                      "roll the dice",
                      "roll dice",
                      "throw dice",
                      "my name is {name}",
                      "I am {name}",
                      "Woohoo I am {name}",
                      "Wohoo I am {name}"
                  ]
              },
              {
                  "name": "ContinueGameIntent",
                  "slots": [],
                  "samples": [
                      "continue",
                      "keep going",
                      "roll again"
                  ]
              },
              {
                  "name": "EndGameIntent",
                  "slots": [],
                  "samples": [
                      "end game",
                      "stop playing",
                      "quit"
                  ]
              },
              {
                  "name": "AddScoreIntent",
                  "slots": [
                      {
                          "name": "PlayerName",
                          "type": "AMAZON.US_FIRST_NAME"
                      },
                      {
                          "name": "AddToHighScore",
                          "type": "AddToHighScore"
                      }
                  ],
                  "samples": [
                      "{AddToHighScore} add my score",
                      "{AddToHighScore} add to high score list",
                      "{AddToHighScore} add to high scores",
                      "{AddToHighScore} add me to the high score list"
                  ]
              },
              {
                  "name": "HighScoresIntent",
                  "slots": [],
                  "samples": [
                      "top scores",
                      "top ten scores",
                      "high scores",
                      "leaderboard"
                  ]
              },
              {
                  "name": "AMAZON.HelpIntent",
                  "samples": []
              },
              {
                  "name": "AMAZON.StopIntent",
                  "samples": []
              },
              {
                  "name": "AMAZON.CancelIntent",
                  "samples": []
              },
              {
                  "name": "AMAZON.FallbackIntent",
                  "samples": []
              },
              {
                  "name": "SessionEndedRequest",
                  "slots": [],
                  "samples": []
              },
              {
                  "name": "AMAZON.NavigateHomeIntent",
                  "samples": []
              }
          ],
          "types": [
              {
                  "name": "YesOrNo",
                  "values": [
                      {
                          "id": "yes",
                          "name": {
                              "value": "yes",
                              "synonyms": [
                                  "yeah"
                              ]
                          }
                      },
                      {
                          "id": "no",
                          "name": {
                              "value": "no",
                              "synonyms": [
                                  "nope"
                              ]
                          }
                      }
                  ]
              },
              {
                  "name": "AddToHighScore",
                  "values": [
                      {
                          "id": "do",
                          "name": {
                              "value": "do",
                              "synonyms": [
                                  "do"
                              ]
                          }
                      },
                      {
                          "id": "dont",
                          "name": {
                              "value": "dont",
                              "synonyms": [
                                  "do not"
                              ]
                          }
                      }
                  ]
              }
          ]
      }
  }
}